management/__init__.py
management/commands/__init__.py
management/commands/load_catalogs.py
migrations/0001_initial.py
migrations/__init__.py
cp_mex-0.0.1.dist-info/METADATA
cp_mex-0.0.1.dist-info/WHEEL
cp_mex-0.0.1.dist-info/top_level.txt
cp_mex-0.0.1.dist-info/RECORD
