Metadata-Version: 2.1
Name: cp-mex
Version: 0.0.1
Summary: Permite migrar los codigos postales de México
Home-page: UNKNOWN
License: UNKNOWN
Platform: UNKNOWN
Requires-Dist: django
